Metadata-Version: 2.1
Name: postpic
Version: 0.5
Summary: The open source particle-in-cell post processor.
Home-page: https://github.com/skuschel/postpic
Author: Stephan Kuschel
Author-email: stephan.kuschel@gmail.de
License: GPLv3+
Keywords: PIC,particle-in-cell,plasma,physics,plasma physics,laser,laser plasma,particle acceleration
Classifier: Development Status :: 4 - Beta
Classifier: Intended Audience :: Science/Research
Classifier: Intended Audience :: Developers
Classifier: Topic :: Scientific/Engineering
Classifier: Topic :: Scientific/Engineering :: Astronomy
Classifier: Topic :: Scientific/Engineering :: Physics
Classifier: Topic :: Scientific/Engineering :: Visualization
Classifier: Programming Language :: Python
Classifier: Programming Language :: Python :: 2.7
Classifier: Programming Language :: Python :: 3
Classifier: Programming Language :: Python :: 3.5
Classifier: Programming Language :: Python :: 3.6
Classifier: Operating System :: Unix
Classifier: Operating System :: MacOS
Classifier: Operating System :: Microsoft :: Windows
Classifier: Operating System :: POSIX
Classifier: License :: OSI Approved :: GNU General Public License v3 or later (GPLv3+)
Provides-Extra: h5 reader for openPMD support
Provides-Extra: sdf support for EPOCH reader
Provides-Extra: PyPNG read png files
Provides-Extra: Pillow to read other image files
License-File: LICENSE
